patrowl4py/__init__.py
patrowl4py/api.py
patrowl4py/constants.py
patrowl4py/exceptions.py
Patrowl4py-1.1.9.dist-info/LICENSE
Patrowl4py-1.1.9.dist-info/METADATA
Patrowl4py-1.1.9.dist-info/WHEEL
Patrowl4py-1.1.9.dist-info/top_level.txt
Patrowl4py-1.1.9.dist-info/RECORD
