Metadata-Version: 2.1
Name: Patrowl4py
Version: 1.1.9
Summary: Python API for PatrowlManager (Community and Pro editions)
Home-page: https://github.com/Patrowl/Patrowl4py
Author: Nicolas Mattiocco
Author-email: getsupport@patrowl.io
License: AGPLv3
Platform: UNKNOWN
License-File: LICENSE
